zcmds_win32/__init__.py
zcmds_win32/_exec.py
zcmds_win32/install_tool.py
zcmds_win32/settings.py
zcmds_win32/unix_tool_path.py
zcmds_win32/cmds/[.py
zcmds_win32/cmds/arch.py
zcmds_win32/cmds/awk.py
zcmds_win32/cmds/basename.py
zcmds_win32/cmds/cat.py
zcmds_win32/cmds/cp.py
zcmds_win32/cmds/date.py
zcmds_win32/cmds/dig.py
zcmds_win32/cmds/dirname.py
zcmds_win32/cmds/du.py
zcmds_win32/cmds/fixvmmem.py
zcmds_win32/cmds/git_bash.py
zcmds_win32/cmds/grep.py
zcmds_win32/cmds/home.py
zcmds_win32/cmds/id.py
zcmds_win32/cmds/ls.py
zcmds_win32/cmds/make.py
zcmds_win32/cmds/md5sum.py
zcmds_win32/cmds/mv.py
zcmds_win32/cmds/nano.py
zcmds_win32/cmds/open.py
zcmds_win32/cmds/pico.py
zcmds_win32/cmds/pip3.py
zcmds_win32/cmds/ps.py
zcmds_win32/cmds/pwd.py
zcmds_win32/cmds/realpath.py
zcmds_win32/cmds/rm.py
zcmds_win32/cmds/sed.py
zcmds_win32/cmds/tee.py
zcmds_win32/cmds/touch.py
zcmds_win32/cmds/uname.py
zcmds_win32/cmds/uniq.py
zcmds_win32/cmds/unzip.py
zcmds_win32/cmds/wc.py
zcmds_win32/cmds/which.py
zcmds_win32/cmds/xargs.py
zcmds_win32/cmds/yes.py
zcmds_win32/cmds/zcmds_win32.py
zcmds_win32-1.2.29.dist-info/METADATA
zcmds_win32-1.2.29.dist-info/WHEEL
zcmds_win32-1.2.29.dist-info/entry_points.txt
zcmds_win32-1.2.29.dist-info/top_level.txt
zcmds_win32-1.2.29.dist-info/RECORD
