Metadata-Version: 2.4
Name: zcmds_win32
Version: 1.2.29
Summary: Cross platform(ish) productivity commands written in python.
License: BSD 3-Clause License
Keywords: zcmds,win32,zcmds_win32,zcmds-win32,cli,command line,command line interface
Classifier: Programming Language :: Python :: 3
Requires-Python: >=3.10
Requires-Dist: sudo_win32[sudo]
Requires-Dist: download
